gcmt/__init__.py
gcmt/cli.py
gcmt-1.0.1.dist-info/METADATA
gcmt-1.0.1.dist-info/WHEEL
gcmt-1.0.1.dist-info/entry_points.txt
gcmt-1.0.1.dist-info/licenses/LICENSE
gcmt-1.0.1.dist-info/RECORD
